llmeter/__init__.py
llmeter/callbacks/__init__.py
llmeter/callbacks/base.py
llmeter/callbacks/cost/__init__.py
llmeter/callbacks/cost/dimensions.py
llmeter/callbacks/cost/model.py
llmeter/callbacks/cost/providers/__init__.py
llmeter/callbacks/cost/providers/sagemaker.py
llmeter/callbacks/cost/results.py
llmeter/callbacks/cost/serde.py
llmeter/callbacks/mlflow.py
llmeter/endpoints/__init__.py
llmeter/endpoints/base.py
llmeter/endpoints/bedrock.py
llmeter/endpoints/litellm.py
llmeter/endpoints/openai.py
llmeter/endpoints/sagemaker.py
llmeter/experiments.py
llmeter/plotting/__init__.py
llmeter/plotting/heatmap.py
llmeter/plotting/plotting.py
llmeter/prompt_utils.py
llmeter/results.py
llmeter/runner.py
llmeter/tokenizers.py
llmeter/utils.py
llmeter-0.1.7.dist-info/METADATA
llmeter-0.1.7.dist-info/WHEEL
llmeter-0.1.7.dist-info/licenses/LICENSE
llmeter-0.1.7.dist-info/licenses/NOTICE
llmeter-0.1.7.dist-info/RECORD
