Metadata-Version: 2.4
Name: llmeter
Version: 0.1.7
Summary: A lightweight, cross-platform latency and throughput profiler for LLMs
License: Apache-2.0
License-File: LICENSE
License-File: NOTICE
Keywords: llm,genai,testing,performance
Author: Amazon Web Services
Maintainer: llmeter-maintainers
Maintainer-email: llmeter-maintainers@amazon.com
Requires-Python: >=3.10,<3.13
Classifier: License :: OSI Approved :: Apache Software License
Classifier: Programming Language :: Python :: 3
Classifier: Programming Language :: Python :: 3.10
Classifier: Programming Language :: Python :: 3.11
Classifier: Programming Language :: Python :: 3.12
Provides-Extra: all
Provides-Extra: litellm
Provides-Extra: mlflow
Provides-Extra: openai
Provides-Extra: plotting
Requires-Dist: boto3 (>=1.34.129)
Requires-Dist: fsspec[http,s3] (>=2023.6.0)
Requires-Dist: jmespath (>=0.7.1,<2.0.0)
Requires-Dist: kaleido (<=0.2.1) ; extra == "all" or extra == "plotting"
Requires-Dist: litellm (>=1.47.1) ; extra == "all" or extra == "litellm"
Requires-Dist: mlflow-skinny (>=2.13.0) ; extra == "all" or extra == "mlflow"
Requires-Dist: openai (>=1.35.1) ; extra == "all" or extra == "openai"
Requires-Dist: pandas (>=2.2.0) ; extra == "all" or extra == "plotting"
Requires-Dist: plotly (>=5.24.1,<6.0.0) ; extra == "all" or extra == "plotting"
Requires-Dist: tqdm (>=4.66.0)
Requires-Dist: universal-pathlib (>=0.2.1)
Project-URL: Repository, https://github.com/awslabs/llmeter
